{
	"configurations" : 
	[
		{
			"directories" : 
			[
				{
					"build" : ".",
					"hasInstallRule" : true,
					"jsonFile" : "directory-.-858f7988a1aa540cd604.json",
					"minimumCMakeVersion" : 
					{
						"string" : "3.20"
					},
					"projectIndex" : 0,
					"source" : ".",
					"targetIndexes" : 
					[
						0,
						1
					]
				}
			],
			"name" : "",
			"projects" : 
			[
				{
					"directoryIndexes" : 
					[
						0
					],
					"name" : "robot_app",
					"targetIndexes" : 
					[
						0,
						1
					]
				}
			],
			"targets" : 
			[
				{
					"directoryIndex" : 0,
					"id" : "robot_app_uninstall::@6890427a1f51a3e7e1df",
					"jsonFile" : "target-robot_app_uninstall-883850a96bedc90cd371.json",
					"name" : "robot_app_uninstall",
					"projectIndex" : 0
				},
				{
					"directoryIndex" : 0,
					"id" : "uninstall::@6890427a1f51a3e7e1df",
					"jsonFile" : "target-uninstall-b9259ba50235c63e86fb.json",
					"name" : "uninstall",
					"projectIndex" : 0
				}
			]
		}
	],
	"kind" : "codemodel",
	"paths" : 
	{
		"build" : "/home/natalia/Documents/STUDING/robotix/modul6/ex05/build/robot_app",
		"source" : "/home/natalia/Documents/STUDING/robotix/modul6/ex05/robot_app"
	},
	"version" : 
	{
		"major" : 2,
		"minor" : 6
	}
}
